ntelebot/__init__.py
ntelebot/bot.py
ntelebot/conftest.py
ntelebot/deeplink.py
ntelebot/delayqueue.py
ntelebot/dispatch.py
ntelebot/errors.py
ntelebot/invislink.py
ntelebot/keyboardutil.py
ntelebot/limits.py
ntelebot/loop.py
ntelebot/preprocess.py
ntelebot/requests.py
ntelebot/test_bot.py
ntelebot/test_deeplink.py
ntelebot/test_delayqueue.py
ntelebot/test_dispatch.py
ntelebot/test_errors.py
ntelebot/test_invislink.py
ntelebot/test_keyboardutil.py
ntelebot/test_limits.py
ntelebot/test_loop.py
ntelebot/test_preprocess.py
ntelebot-0.4.6.dist-info/METADATA
ntelebot-0.4.6.dist-info/WHEEL
ntelebot-0.4.6.dist-info/top_level.txt
ntelebot-0.4.6.dist-info/RECORD
