Metadata-Version: 2.4
Name: ntelebot
Version: 0.4.6
Summary: A simple implementation of https://core.telegram.org/bots/api.
Author-email: Daniel Reed <nmlorg@gmail.com>
Project-URL: Homepage, https://github.com/nmlorg/ntelebot
Project-URL: Issues, https://github.com/nmlorg/ntelebot/issues
Requires-Python: >=3.10
Requires-Dist: requests
Provides-Extra: dev
Requires-Dist: pylint; extra == "dev"
Requires-Dist: pytest-cov; extra == "dev"
Requires-Dist: pytest; extra == "dev"
Requires-Dist: requests-mock; extra == "dev"
